{
  "id": "2717f5d1-d908-403b-acfd-4db734e47381",
  "prevId": "06a19390-f4e6-454d-b9ba-955d9b949602",
  "version": "7",
  "dialect": "postgresql",
  "tables": {
    "den.books": {
      "name": "books",
      "schema": "den",
      "columns": {
        "id": {
          "name": "id",
          "type": "bigint",
          "primaryKey": true,
          "notNull": true,
          "identity": {
            "type": "always",
            "name": "books_id_seq",
            "schema": "den",
            "increment": "1",
            "startWith": "1",
            "minValue": "1",
            "maxValue": "9223372036854775807",
            "cache": "1",
            "cycle": false
          }
        },
        "isbn": {
          "name": "isbn",
          "type": "text",
          "primaryKey": false,
          "notNull": false
        },
        "title": {
          "name": "title",
          "type": "text",
          "primaryKey": false,
          "notNull": true
        },
        "author": {
          "name": "author",
          "type": "text",
          "primaryKey": false,
          "notNull": true
        },
        "cover": {
          "name": "cover",
          "type": "text",
          "primaryKey": false,
          "notNull": false
        },
        "description": {
          "name": "description",
          "type": "text",
          "primaryKey": false,
          "notNull": false
        },
        "created_at": {
          "name": "created_at",
          "type": "timestamp",
          "primaryKey": false,
          "notNull": true,
          "default": "now()"
        },
        "updated_at": {
          "name": "updated_at",
          "type": "timestamp",
          "primaryKey": false,
          "notNull": true,
          "default": "now()"
        }
      },
      "indexes": {},
      "foreignKeys": {},
      "compositePrimaryKeys": {},
      "uniqueConstraints": {},
      "policies": {
        "books-select-policy": {
          "name": "books-select-policy",
          "as": "PERMISSIVE",
          "for": "SELECT",
          "to": [
            "anon",
            "authenticated"
          ],
          "using": "true"
        }
      },
      "checkConstraints": {},
      "isRLSEnabled": false
    },
    "den.profile_books": {
      "name": "profile_books",
      "schema": "den",
      "columns": {
        "profile_id": {
          "name": "profile_id",
          "type": "uuid",
          "primaryKey": false,
          "notNull": false
        },
        "book_id": {
          "name": "book_id",
          "type": "bigint",
          "primaryKey": false,
          "notNull": false
        },
        "source": {
          "name": "source",
          "type": "book_sources",
          "typeSchema": "den",
          "primaryKey": false,
          "notNull": true
        },
        "source_etc": {
          "name": "source_etc",
          "type": "text",
          "primaryKey": false,
          "notNull": false
        },
        "read_state": {
          "name": "read_state",
          "type": "read_state",
          "typeSchema": "den",
          "primaryKey": false,
          "notNull": true,
          "default": "'toread'"
        },
        "comment": {
          "name": "comment",
          "type": "text",
          "primaryKey": false,
          "notNull": true
        },
        "created_at": {
          "name": "created_at",
          "type": "timestamp",
          "primaryKey": false,
          "notNull": true,
          "default": "now()"
        },
        "updated_at": {
          "name": "updated_at",
          "type": "timestamp",
          "primaryKey": false,
          "notNull": true,
          "default": "now()"
        }
      },
      "indexes": {},
      "foreignKeys": {
        "profile_books_profile_id_profiles_id_fk": {
          "name": "profile_books_profile_id_profiles_id_fk",
          "tableFrom": "profile_books",
          "tableTo": "profiles",
          "schemaTo": "den",
          "columnsFrom": [
            "profile_id"
          ],
          "columnsTo": [
            "id"
          ],
          "onDelete": "cascade",
          "onUpdate": "no action"
        },
        "profile_books_book_id_books_id_fk": {
          "name": "profile_books_book_id_books_id_fk",
          "tableFrom": "profile_books",
          "tableTo": "books",
          "schemaTo": "den",
          "columnsFrom": [
            "book_id"
          ],
          "columnsTo": [
            "id"
          ],
          "onDelete": "cascade",
          "onUpdate": "no action"
        }
      },
      "compositePrimaryKeys": {},
      "uniqueConstraints": {},
      "policies": {
        "profile_books-select-policy": {
          "name": "profile_books-select-policy",
          "as": "PERMISSIVE",
          "for": "SELECT",
          "to": [
            "authenticated",
            "service_role"
          ],
          "using": "(select auth.uid()) = \"den\".\"profile_books\".\"profile_id\""
        },
        "profile_books-insert-policy": {
          "name": "profile_books-insert-policy",
          "as": "PERMISSIVE",
          "for": "INSERT",
          "to": [
            "authenticated"
          ],
          "withCheck": "(select auth.uid()) = \"den\".\"profile_books\".\"profile_id\""
        },
        "profile_books-update-policy": {
          "name": "profile_books-update-policy",
          "as": "PERMISSIVE",
          "for": "UPDATE",
          "to": [
            "authenticated"
          ],
          "using": "(select auth.uid()) = \"den\".\"profile_books\".\"profile_id\""
        },
        "profile_books-delete-policy": {
          "name": "profile_books-delete-policy",
          "as": "PERMISSIVE",
          "for": "DELETE",
          "to": [
            "authenticated"
          ],
          "using": "(select auth.uid()) = \"den\".\"profile_books\".\"profile_id\""
        }
      },
      "checkConstraints": {},
      "isRLSEnabled": false
    },
    "den.profiles": {
      "name": "profiles",
      "schema": "den",
      "columns": {
        "id": {
          "name": "id",
          "type": "uuid",
          "primaryKey": true,
          "notNull": true
        },
        "name": {
          "name": "name",
          "type": "text",
          "primaryKey": false,
          "notNull": true
        },
        "username": {
          "name": "username",
          "type": "text",
          "primaryKey": false,
          "notNull": true
        },
        "email": {
          "name": "email",
          "type": "text",
          "primaryKey": false,
          "notNull": false
        },
        "avatar": {
          "name": "avatar",
          "type": "text",
          "primaryKey": false,
          "notNull": false
        },
        "bio": {
          "name": "bio",
          "type": "text",
          "primaryKey": false,
          "notNull": false
        },
        "created_at": {
          "name": "created_at",
          "type": "timestamp",
          "primaryKey": false,
          "notNull": true,
          "default": "now()"
        },
        "updated_at": {
          "name": "updated_at",
          "type": "timestamp",
          "primaryKey": false,
          "notNull": true,
          "default": "now()"
        }
      },
      "indexes": {},
      "foreignKeys": {
        "profiles_id_users_id_fk": {
          "name": "profiles_id_users_id_fk",
          "tableFrom": "profiles",
          "tableTo": "users",
          "schemaTo": "auth",
          "columnsFrom": [
            "id"
          ],
          "columnsTo": [
            "id"
          ],
          "onDelete": "cascade",
          "onUpdate": "no action"
        }
      },
      "compositePrimaryKeys": {},
      "uniqueConstraints": {},
      "policies": {
        "profiles-select-policy": {
          "name": "profiles-select-policy",
          "as": "PERMISSIVE",
          "for": "SELECT",
          "to": [
            "authenticated"
          ],
          "using": "(select auth.uid()) = \"den\".\"profiles\".\"id\""
        },
        "profiles-insert-policy": {
          "name": "profiles-insert-policy",
          "as": "PERMISSIVE",
          "for": "INSERT",
          "to": [
            "authenticated"
          ],
          "withCheck": "(select auth.uid()) = \"den\".\"profiles\".\"id\""
        },
        "profiles-update-policy": {
          "name": "profiles-update-policy",
          "as": "PERMISSIVE",
          "for": "UPDATE",
          "to": [
            "authenticated"
          ],
          "using": "(select auth.uid()) = \"den\".\"profiles\".\"id\""
        },
        "profiles-delete-policy": {
          "name": "profiles-delete-policy",
          "as": "PERMISSIVE",
          "for": "DELETE",
          "to": [
            "authenticated"
          ],
          "using": "(select auth.uid()) = \"den\".\"profiles\".\"id\""
        }
      },
      "checkConstraints": {},
      "isRLSEnabled": false
    }
  },
  "enums": {
    "den.book_sources": {
      "name": "book_sources",
      "schema": "den",
      "values": [
        "kyobo",
        "aladin",
        "yes24",
        "ridibooks",
        "etc"
      ]
    },
    "den.read_state": {
      "name": "read_state",
      "schema": "den",
      "values": [
        "reading",
        "toread",
        "completed"
      ]
    }
  },
  "schemas": {},
  "sequences": {},
  "roles": {},
  "policies": {},
  "views": {},
  "_meta": {
    "columns": {},
    "schemas": {},
    "tables": {}
  }
}